flowcontrol/__init__.py
flowcontrol/actions.py
flowcontrol/admin.py
flowcontrol/apps.py
flowcontrol/base.py
flowcontrol/engine.py
flowcontrol/registry.py
flowcontrol/tasks.py
flowcontrol/utils.py
flowcontrol/management/__init__py
flowcontrol/management/commands/__init__.py
flowcontrol/management/commands/flowcontrol.py
flowcontrol/migrations/0001_initial.py
flowcontrol/migrations/__init__.py
flowcontrol/models/__init__.py
flowcontrol/models/config.py
flowcontrol/models/core.py
flowcontrol/templates/admin/flowcontrol/flow/change_form.html
flowcontrol/templates/flowcontrol/admin/flowaction_add.html
flowcontrol/templates/flowcontrol/admin/flowaction_changelist.html
django_flowcontrol-0.0.2.dist-info/METADATA
django_flowcontrol-0.0.2.dist-info/WHEEL
django_flowcontrol-0.0.2.dist-info/licenses/LICENSE
django_flowcontrol-0.0.2.dist-info/RECORD
