Metadata-Version: 2.4
Name: django-flowcontrol
Version: 0.0.2
Summary: Design and run workflows in Django
License-File: LICENSE
Requires-Python: >=3.10
Requires-Dist: django-treebeard
Requires-Dist: django>=5.2
Requires-Dist: python-dateutil
